{
  "project_info": {
    "project_number": "998668501053",
    "project_id": "order-tracking-system-b3db2",
    "storage_bucket": "order-tracking-system-b3db2.appspot.com"
  },
  "client": [
    {
      "client_info": {
        "mobilesdk_app_id": "1:998668501053:android:ff2a79154e8e718e4f2a54",
        "android_client_info": {
          "package_name": "com.android.application"
        }
      },
      "oauth_client": [
        {
          "client_id": "998668501053-uubdsr7jnsf511tgt63vqi3oiulovado.apps.googleusercontent.com",
          "client_type": 3
        }
      ],
      "api_key": [
        {
          "current_key": "AIzaSyBbBGDeNHSc6AxkCMe3lQP4uVV0fjcqCNA"
        }
      ],
      "services": {
        "appinvite_service": {
          "other_platform_oauth_client": [
            {
              "client_id": "998668501053-uubdsr7jnsf511tgt63vqi3oiulovado.apps.googleusercontent.com",
              "client_type": 3
            }
          ]
        }
      }
    }
  ],
  "configuration_version": "1"
}